indecode.py
indecode-1.5.2.dist-info/METADATA
indecode-1.5.2.dist-info/WHEEL
indecode-1.5.2.dist-info/top_level.txt
indecode-1.5.2.dist-info/RECORD
