Metadata-Version: 2.1
Name: indecode
Version: 1.5.2
Summary: Code and decode string
Author: lolo859
Keywords: code,incode,indecode,decode,incode,indc
Classifier: Natural Language :: French
Classifier: Topic :: Security :: Cryptography
Classifier: Topic :: Software Development :: Code Generators
Requires-Dist: docutils >=0.3
Requires-Dist: pillow
